README.md
drawaframe.py
setup.py
drawaframe.egg-info/PKG-INFO
drawaframe.egg-info/SOURCES.txt
drawaframe.egg-info/dependency_links.txt
drawaframe.egg-info/entry_points.txt
drawaframe.egg-info/top_level.txt