Metadata-Version: 1.0
Name: drawaframe
Version: 0.1.0
Summary: A simple way to generate decorative frames for CLI applications.
Home-page: https://github.com/jagadeesh-kotra/drawaframe
Author: Jagadeesh Kotra
Author-email: hello@jagadeesh.me
License: Apache
Platform: UNKNOWN
